oc_portal_commons/__init__.py
oc_portal_commons/artifacts_listings.py
oc_portal_commons/forms.py
oc_portal_commons/search.py
oc_portal_commons/views_errors.py
oc_portal_commons/views_utils.py
oc_portal_commons/static/ajax-loader.gif
oc_portal_commons/static/custom.css
oc_portal_commons/static/general.css
oc_portal_commons/static/js/custom_scripts.js
oc_portal_commons/templates/dl/404.html
oc_portal_commons/templates/dl/500.html
oc_portal_commons/templates/dl/actions.html
oc_portal_commons/templates/dl/app_index.html
oc_portal_commons/templates/dl/base.html
oc_portal_commons/templates/dl/base_site.html
oc_portal_commons/templates/dl/change_form.html
oc_portal_commons/templates/dl/change_list.html
oc_portal_commons/templates/dl/change_list_results.html
oc_portal_commons/templates/dl/date_hierarchy.html
oc_portal_commons/templates/dl/delete_confirmation.html
oc_portal_commons/templates/dl/delete_selected_confirmation.html
oc_portal_commons/templates/dl/filter.html
oc_portal_commons/templates/dl/index.html
oc_portal_commons/templates/dl/invalid_setup.html
oc_portal_commons/templates/dl/login.html
oc_portal_commons/templates/dl/object_history.html
oc_portal_commons/templates/dl/pagination.html
oc_portal_commons/templates/dl/popup_response.html
oc_portal_commons/templates/dl/prepopulated_fields_js.html
oc_portal_commons/templates/dl/related_widget_wrapper.html
oc_portal_commons/templates/dl/search_form.html
oc_portal_commons/templates/dl/submit_line.html
oc_portal_commons/templates/dl/includes/fieldset.html
oc_portal_commons/templates/dl/includes/object_delete_summary.html
oc_portal_commons/templates/portal_commons/404.html
oc_portal_commons/templates/portal_commons/500.html
oc_portal_commons/templates/portal_commons/_base.html
oc_portal_commons/templates/portal_commons/_base_site.html
oc_portal_commons/templates/portal_commons/includes/delivery_messages.html
oc_portal_commons/templates/registration/logged_out.html
oc_portal_commons/templates/registration/login.html
oc_portal_commons-11.0.4.dist-info/LICENSE
oc_portal_commons-11.0.4.dist-info/METADATA
oc_portal_commons-11.0.4.dist-info/WHEEL
oc_portal_commons-11.0.4.dist-info/top_level.txt
oc_portal_commons-11.0.4.dist-info/RECORD
