Metadata-Version: 2.1
Name: oc-portal-commons
Version: 11.0.4
Summary: Common code, static files, settings and testing tools used at all portal variants
Requires-Python: >=3.6
License-File: LICENSE
Requires-Dist: oc-delivery-apps (>=11.2.8)
Requires-Dist: packaging
Requires-Dist: pyparsing (==2.4.0)
Requires-Dist: django-jquery
Requires-Dist: django-tests
Requires-Dist: django-filter
Requires-Dist: fs
